README.md
easy_ptvsd.py
setup.py
easy_ptvsd.egg-info/PKG-INFO
easy_ptvsd.egg-info/SOURCES.txt
easy_ptvsd.egg-info/dependency_links.txt
easy_ptvsd.egg-info/requires.txt
easy_ptvsd.egg-info/top_level.txt