Metadata-Version: 1.1
Name: easy-ptvsd
Version: 0.1.0
Summary: A convenience package for PTVSD.
Home-page: https://github.com/colinfike/easy-ptvsd
Author: Colin Fike
Author-email: colin.fike@gmail.com
License: MIT
Keywords: ptvsd easy python remote debugging
Platform: UNKNOWN
Classifier: Development Status :: 3 - Alpha
Classifier: Intended Audience :: Developers
Classifier: Topic :: Software Development
Classifier: Programming Language :: Python :: 3
